<?xml version="1.0" ?>
<annotation>
	<folder>/Users/apple/Documents/Git/OderFit-Zalo_AI_Hacka/zai2019_hackaton_train/images/train/</folder>
	<filename>127.jpg</filename>
	<path>/Users/apple/Documents/Git/OderFit-Zalo_AI_Hacka/zai2019_hackaton_train/images/train/127.jpg</path>
	<source>
		<database>Unknown</database>
	</source>
	<size>
		<width>986</width>
		<height>1212</height>
		<depth>3</depth>
	</size>
	<segmented>0</segmented>
	<object>
		<name>Nightlight</name>
		<pose>Unspecified</pose>
		<truncated>0</truncated>
		<difficult>0</difficult>
		<bndbox>
			<xmin>266</xmin>
			<ymin>333</ymin>
			<xmax>767</xmax>
			<ymax>1032</ymax>
		</bndbox>
	</object>
</annotation>
